Workbook

Sheet Register
A1: ID | B1: Audit | C1: Finding | D1: Severity | E1: Fix class | F1: Status | G1: Verification | H1: Verification note / evidence
A2: SEC-C1 | B2: Security | C2: Live production credentials and employee PII committed to the repo, in the one path CI is told not to scan | D2: Critical | E2: Process + purge | F2: Fixed | G2: Verified in code | H2: Scanner un-excluded AND pattern set widened; 7 credential files cleaned (5 more than the audit cited, incl. 2 Groq keys CI found). CREDENTIALS ROTATED BY OWNER 2026-08-04. History still contains them — purge declined, rotation makes it harmless.
A3: SEC-C2 | B3: Security | C3: Logout does not end the session; the refresh token stays valid | D3: Critical | E3: Code, quick | F3: Fixed | G3: Verified in code | H3: Access tokens now carry `sid`; logout revokes the session from the TOKEN, not a body field the client never sent. Both issuance paths (login + refresh rotation) carry it — a test asserts every signAccessToken call site does. Response reports session_revoked honestly. Verified to FAIL 4/6 against the old service. Commit 809caad.
A4: SEC-C3 | B4: Security | C4: No brute-force protection on any authentication endpoint; failed-login counter never enforced | D4: Critical | E4: Code, quick | F4: Fixed | G4: Verified in code | H4: Limiters on all 11 credential surfaces across 3 tiers, AND the failed-login counter is now enforced as a decaying cooldown (migration 0495). 7 assertions on the curve.
A5: SEC-H1 | B5: Security | C5: The AI assistant executes business writes with no permission check at all | D5: High | E5: Code | F5: Open | G5: As reported
A6: SEC-H2 | B6: Security | C6: Platform Console credential-store routes have no capability gate | D6: High | E6: Code, quick | F6: Fixed | G6: Verified in code | H6: requireCap on all 8 routes; settings.read/write + migration 0032; structural test asserts all 47 platform routes are gated.
A7: SEC-H3 | B7: Security | C7: Request-body keys become SQL column identifiers on modules using the passthrough validator | D7: High | E7: Code | F7: Open | G7: As reported
A8: SEC-H4 | B8: Security | C8: MOD-67 'edit' can take over any account, including the CEO, with no re-authentication | D8: High | E8: Code | F8: Open | G8: As reported
A9: SEC-H5 | B9: Security | C9: Rate limiting is bypassable: trust proxy true with an IP-keyed in-memory store | D9: High | E9: Config + code | F9: Fixed | G9: Verified in code | H9: Redis-backed limiter store; trust proxy is now a hop count (TRUST_PROXY_HOPS), not `true`.
A10: SEC-H6 | B10: Security | C10: Portal and platform accounts protected by an 8-char password, no complexity or breach check | D10: High | E10: Code, quick | F10: Open | G10: As reported
A11: SEC-M1 | B11: Security | C11: Access tokens are not session-bound: revocation does not revoke | D11: Medium | E11: Code | F11: Open | G11: As reported
A12: SEC-M2 | B12: Security | C12: killSession has no ownership predicate | D12: Medium | E12: Code, quick | F12: Fixed | G12: Verified in code | H12: killSession is now always scoped to the acting user. Folded into the SEC-C2 fix. Commit 809caad.
A13: SEC-M3 | B13: Security | C13: Document vault authorization is module-level, not record-level | D13: Medium | E13: Code | F13: Open | G13: As reported
A14: SEC-M4 | B14: Security | C14: The Socket.IO handshake lets the client name its own tenant | D14: Medium | E14: Code | F14: Open | G14: As reported
A15: SEC-M5 | B15: Security | C15: One JWT secret across all three auth tiers, and no tenant claim in any token | D15: Medium | E15: Structural | F15: Open | G15: As reported
A16: SEC-M6 | B16: Security | C16: Platform tier has no session store, no revocation and no 2FA | D16: Medium | E16: Structural | F16: Open | G16: As reported
A17: SEC-M7 | B17: Security | C17: One database credential and one encryption key shared across all tenants | D17: Medium | E17: Structural | F17: Open | G17: As reported
A18: SEC-M8 | B18: Security | C18: CSP permits unsafe-inline scripts application-wide | D18: Medium | E18: Config | F18: Open | G18: Verified in code | H18: server.js: script-src ['self','unsafe-inline'], script-src-attr ['unsafe-inline']
A19: SEC-M9 | B19: Security | C19: Dependency vulnerabilities present, gate non-blocking, no SAST or Dependabot | D19: Medium | E19: CI | F19: Open | G19: Verified in code | H19: ci.yaml:79 continue-on-error: true on npm audit
A20: SEC-L1 | B20: Security | C20: Containers run as root; compose bind-mounts the document vault into them | D20: Low | E20: Config, quick | F20: Open | G20: As reported
A21: SEC-L2 | B21: Security | C21: Redis unauthenticated and keyspace not tenant-namespaced; invalidateGrants uses blocking KEYS | D21: Low | E21: Config + code | F21: Open | G21: As reported
A22: SEC-L3 | B22: Security | C22: Refresh token in web storage | D22: Low | E22: Code (blocked by M8, C2) | F22: Open | G22: As reported
A23: SEC-L4 | B23: Security | C23: Logger redaction misses refresh_token, access_token, password_hash, totp_secret_enc, secret_enc | D23: Low | E23: Config, quick | F23: Fixed | G23: Verified in code | H23: REDACT_PATHS widened; both top-level and nested forms generated from SENSITIVE_KEYS.
A24: SEC-L5 | B24: Security | C24: The anonymous-surface test is shallow - matches authMiddleware anywhere in the router | D24: Low | E24: Test, quick | F24: Open | G24: As reported
A25: SEC-L6 | B25: Security | C25: src/middleware/audit.js is dead code, never imported or mounted | D25: Low | E25: Delete | F25: Open | G25: As reported
A26: DI-5.5 | B26: Data Integrity | C26: Asset depreciation never posts to the GL and records itself as posted | D26: Critical | E26: Code, quick | F26: Fixed | G26: Verified in code | H26: Depreciation now reaches the GL: account_code + sourceDocRef, and a ledger rejection FAILS the call instead of setting posted=true with entry_id NULL. 11 assertions, verified to FAIL against the pre-fix file. Sweep found only asset+payroll; a grep-as-a-test blocks a third. Commit 62a9646. NOTE: existing bad rows need scripts/db/reconcile-depreciation.js.
A27: DI-5.1 | B27: Data Integrity | C27: Inventory balance: no transaction, no lock, no DB floor | D27: Critical | E27: Code + constraint | F27: Open | G27: As reported
A28: DI-5.2 | B28: Data Integrity | C28: Shared CRUD kit writes business row, event and audit as three separate commits | D28: Critical | E28: Code, mechanical | F28: Open | G28: As reported
A29: DI-1.1 | B29: Data Integrity | C29: ~100 money/quantity columns with no CHECK constraint | D29: Critical | E29: Migration + data probe | F29: Open | G29: As reported
A30: DI-1.2 | B30: Data Integrity | C30: No cross-row sum invariants (over-allocation, over-justification) | D30: Critical | E30: Migration + data probe | F30: Open | G30: As reported
A31: DI-2.1 | B31: Data Integrity | C31: ON DELETE CASCADE on financial and inventory history | D31: Critical | E31: Migration, careful | F31: Open | G31: As reported
A32: DI-1.3 | B32: Data Integrity | C32: Multi-currency ledger lines are stored but never reconciled to a base currency | D32: High | E32: Migration + code | F32: Open | G32: As reported
A33: DI-1.6 | B33: Data Integrity | C33: doc_number is not unique anywhere | D33: High | E33: Migration + dedupe | F33: Open | G33: As reported
A34: DI-1.8 | B34: Data Integrity | C34: tax_code effective windows can overlap, producing wrong VAT silently | D34: High | E34: Migration + code | F34: Open | G34: As reported
A35: DI-1.9 | B35: Data Integrity | C35: cached_receivables read but never written; credit limit inert | D35: High | E35: Code, quick | F35: Open | G35: As reported
A36: DI-2.2 | B36: Data Integrity | C36: 295 of 351 foreign keys have no index on the referencing column | D36: High | E36: Migration, online | F36: Open | G36: As reported
A37: DI-2.4 | B37: Data Integrity | C37: Sandbox actor-FK guard applied inconsistently | D37: High | E37: Code + design | F37: Open | G37: As reported
A38: DI-3.1 | B38: Data Integrity | C38: Migration application is not atomic with its ledger entry | D38: High | E38: Tooling | F38: Open | G38: As reported
... A40: DI-3.3 | B40: Data Integrity | C40: Migration files and the live schema have already drifted (notification_preference) | D40: High | E40: Verify + tooling | F40: Open | G40: As reported
A41: DI-3.5 | B41: Data Integrity | C41: No migration is reversible; no down concept exists in the tooling | D41: High | E41: Policy | F41: Partially fixed | G41: As reported | H41: New migrations must declare -- DOWN or -- IRREVERSIBLE (CI gate). The 92 pre-existing migrations are still irreversible and deliberately not retro-fitted.
A42: DI-5.3 | B42: Data Integrity | C42: Receipt allocation reads unlocked and can over-allocate | D42: High | E42: Code + constraint | F42: Open | G42: As reported
A43: DI-5.4 | B43: Data Integrity | C43: Tax-code supersession splits across two transactions | D43: High | E43: Code, quick | F43: Open | G43: As reported
A44: DI-6.2 | B44: Data Integrity | C44: Audit tamper-evidence chain declared but before_hash/after_hash never populated | D44: High | E44: Code, quick | F44: Open | G44: As reported
A45: DI-6.3 | B45: Data Integrity | C45: Financial and inventory mutations audited inconsistently; depends on service discipline | D45: High | E45: Code + triggers | F45: Open | G45: As reported
A46: DI-6.4 | B46: Data Integrity | C46: stock_movement is mutable, cascade-deleted, and can be incomplete - no audit trail | D46: High | E46: Migration | F46: Open | G46: As reported
A47: DI-7.1 | B47: Data Integrity | C47: Missing uniqueness on document numbers and payment allocations | D47: High | E47: Migration + dedupe | F47: Open | G47: As reported
A48: DI-1.4 | B48: Data Integrity | C48: currency typing inconsistent - 8 columns FK to currency(code), 9 identical ones do not | D48: Medium | E48: Migration | F48: Open | G48: As reported
A49: DI-1.5 | B49: Data Integrity | C49: chart_of_accounts and other self-referencing hierarchies have no cycle guard | D49: Medium | E49: Migration | F49: Open | G49: As reported
A50: DI-2.3 | B50: Data Integrity | C50: No ON UPDATE clause on any foreign key | D50: Medium | E50: Decision | F50: Open | G50: As reported
A51: DI-3.4 | B51: Data Integrity | C51: Duplicate migration numbers - correctly diagnosed and correctly left alone | D51: Medium | E51: Prevention only | F51: Open | G51: As reported
A52: DI-3.6 | B52: Data Integrity | C52: EXCEPTION WHEN OTHERS THEN NULL in data-seeding migrations 0467/0468 | D52: Medium | E52: Forward-fix | F52: Open | G52: As reported
A53: DI-4.1 | B53: Data Integrity | C53: The RLS apparatus references a migration that does not exist | D53: Medium | E53: Remove or implement | F53: Open | G53: As reported
... A58: DI-1.7 | B58: Data Integrity | C58: The section 23.14 dictionary invariant is one-directional | D58: Low | E58: Migration | F58: Open | G58: As reported
A59: OBS-A2 | B59: Observability | C59: The health check is structurally incapable of failing - and it is the deploy gate | D59: Critical | E59: Quick win | F59: Fixed | G59: Verified in code | H59: /api/health/ready probes Postgres+Redis, 503s honestly. Verified with the DB down.
A60: OBS-A1 | B60: Observability | C60: There is no alerting. At all. | D60: Critical | E60: Quick win | F60: Fixed | G60: Verified in code | H60: Repo side wired + loud boot warning. MONITOR AND WEBHOOK CONFIGURED BY OWNER 2026-08-04.
A61: OBS-A3 | B61: Observability | C61: Redis outage boots the app silently degraded | D61: Critical | E61: Quick win | F61: Open | G61: As reported
A62: OBS-A6 | B62: Observability | C62: Dead-lettered business events are a silent black hole | D62: Critical | E62: Medium | F62: Open | G62: As reported
A63: OBS-E1 | B63: Observability | C63: No centralised error tracking of any kind | D63: Critical | E63: Medium | F63: Fixed | G63: Verified in code | H63: shared/observability/error-reporter.js — every 5xx, uncaughtException and unhandledRejection reports with tenant/user/request_id/route/build. Dedupe + id normalisation + frame-drift stability + 20/min ceiling so the channel stays usable. 4xx and ZodError never reported. Commit e78a566.
A64: OBS-E2 | B64: Observability | C64: Frontend errors are completely invisible | D64: Critical | E64: Quick win | F64: Fixed | G64: Verified in code | H64: POST /api/client-errors + client/src/lib/error-reporting.ts covering render, window 'error' and unhandledrejection. ErrorBoundary's dead onError hook now reports by default. sendBeacon survives the post-crash reload. Commit e78a566.
A65: OBS-L1 | B65: Observability | C65: No HTTP access log exists at all - pino-http is a dependency, mounted nowhere | D65: Critical | E65: Quick win | F65: Fixed | G65: Verified in code | H65: pino-http mounted.
A66: OBS-L2 | B66: Observability | C66: The money path is entirely log-silent - zero logger calls in finance or accounting | D66: Critical | E66: Medium | F66: Open | G66: As reported
A67: OBS-L3 | B67: Observability | C67: Almost no log line carries tenant or user, though AsyncLocalStorage already holds both | D67: Critical | E67: Quick win | F67: Fixed | G67: Verified in code | H67: pino mixin injects tenant+user into ALL ~120 call sites with zero edits; auth.js back-fills the user the context captured as null.
A68: OBS-M1 | B68: Observability | C68: No metrics of any kind, no dashboard, no baseline | D68: Critical | E68: Medium | F68: Open | G68: As reported
A69: OBS-T1 | B69: Observability | C69: Reconstructing one failed request is effectively impossible | D69: Critical | E69: Phases 2+4 | F69: Open | G69: As reported
A70: OBS-I1 | B70: Observability | C70: No runbook, no on-call, no incident process | D70: Critical | E70: Process | F70: Open | G70: As reported
A71: OBS-I2 | B71: Observability | C71: No rollback procedure and no artifact to roll back to | D71: Critical | E71: Medium | F71: Fixed | G71: Verified in code | H71: Images tagged by commit and retained; scripts/rollback.sh added.
A72: OBS-A4 | B72: Observability | C72: No restart: policy on any service | D72: High | E72: Quick win | F72: Fixed | G72: Verified in code | H72: restart: unless-stopped on all five services; migrate stays 'no'.
A73: OBS-A5 | B73: Observability | C73: The worker is entirely unmonitored | D73: High | E73: Quick win | F73: Open | G73: As reported
A74: OBS-E3 | B74: Observability | C74: The correlation ID is minted, then thrown away; persisted nowhere | D74: High | E74: Quick / Medium | F74: Open | G74: As reported
A75: OBS-E4 | B75: Observability | C75: uncaughtException keeps a poisoned process alive | D75: High | E75: Quick win | F75: Fixed | G75: Verified in code | H75: Process now exits on uncaughtException; paired with OBS-A4.
A76: OBS-L4 | B76: Observability | C76: Sensitive data leaking into logs, including row values via pg err.detail | D76: High | E76: Quick win | F76: Fixed | G76: Verified in code | H76: Same fix as SEC-L4, incl. pg err.detail. Landed BEFORE any log shipping.
A77: OBS-L7 | B77: Observability | C77: Logs are neither durable nor shipped; lost on every deploy | D77: High | E77: Quick / Medium | F77: Open | G77: As reported
A78: OBS-M2 | B78: Observability | C78: Business metrics unobservable though the data already exists | D78: High | E78: Medium | F78: Open | G78: As reported
A79: OBS-T2 | B79: Observability | C79: No timing recorded anywhere | D79: High | E79: Quick win | F79: Fixed | G79: Verified in code | H79: Response time on every access-log line.
A80: OBS-T4 | B80: Observability | C80: Auth, RBAC and tenant middleware log nothing | D80: High | E80: Quick win | F80: Open | G80: As reported
A81: OBS-I3 | B81: Observability | C81: Migrations have no rollback path and run before the app rolls; no automated backup | D81: High | E81: Medium | F81: Open | G81: As reported
A82: OBS-I4 | B82: Observability | C82: The deploy has no real smoke test and no auto-rollback | D82: High | E82: Quick win | F82: Partially fixed | G82: As reported | H82: Smoke test can now fail and the deploy exits non-zero. Auto-rollback NOT wired — rollback.sh has never been executed, and automating an unproven recovery path is worse than manual.
A83: OBS-I6 | B83: Observability | C83: Single-host topology with no capacity signal | D83: High | E83: Deeper | F83: Open | G83: As reported
A84: OBS-A7 | B84: Observability | C84: Failed BullMQ jobs accumulate unwatched | D84: Medium | E84: Medium | F84: Open | G84: As reported
A85: OBS-L5 | B85: Observability | C85: Level discipline inverted - real failures logged at warn, stacks discarded | D85: Medium | E85: Quick win | F85: Open | G85: As reported
A86: OBS-L6 | B86: Observability | C86: The runbook documents a log location that does not exist | D86: Medium | E86: Quick win | F86: Open | G86: As reported
A87: OBS-M3 | B87: Observability | C87: Slow queries warn but are never measured | D87: Medium | E87: Quick win | F87: Open | G87: As reported
A88: OBS-T3 | B88: Observability | C88: No cross-process correlation into workers | D88: Medium | E88: Medium | F88: Open | G88: As reported
A89: OBS-I5 | B89: Observability | C89: Deploys are unattributed and unannounced | D89: Medium | E89: Quick win | F89: Fixed | G89: Verified in code | H89: Build identity + deploy announcements to ALERT_WEBHOOK_URL on start/success/failure.
A90: API-F1 | B90: API Contract | C90: Eighteen deliberate client errors are returned to consumers as 500 INTERNAL_ERROR | D90: Critical | E90: Code (BC) | F90: Fixed | G90: Verified in code | H90: error-handler honours err.status for 4xx; thrown 5xx still flattens to a generic 500. Fixed BEFORE alerting went live.
A91: API-F6 | B91: API Contract | C91: Two unrelated resources share the base path /inbound | D91: Critical | E91: Code (BC) | F91: Fixed | G91: Verified in code | H91: sales/inbound_intake moved to /intake; 4 client callers updated; waiver list now empty and the boot guard is unconditional. BREAKING.
A92: API-F18 | B92: API Contract | C92: There is no versioning of any kind - no prefix, header, sunset or deprecation mechanism | D92: Critical | E92: Structural | F92: Open | G92: As reported
A93: API-F20 | B93: API Contract | C93: Platform secret management has no capability check (8 routes) | D93: Critical | E93: Code, quick | F93: Fixed | G93: Verified in code | H93: Same fix as SEC-H2.
A94: API-F30 | B94: API Contract | C94: There is no mechanism that would catch a contract regression | D94: Critical | E94: CI + test | F94: Open | G94: As reported
A95: API-F2 | B95: API Contract | C95: Three different response shapes for 'your input was invalid' | D95: High | E95: Code (BC) | F95: Open | G95: As reported
A96: API-F15 | B96: API Contract | C96: 60 write routes accept an unvalidated body (17% of writes) | D96: High | E96: Code | F96: Open | G96: As reported
A97: API-F16 | B97: API Contract | C97: Query and path parameters are almost never validated | D97: High | E97: Code | F97: Open | G97: As reported
A98: API-F19 | B98: API Contract | C98: Modules can vanish from the API without any error | D98: High | E98: Additive | F98: Fixed | G98: Verified in code | H98: Skipped modules recorded, logged at error, and surfaced on /api/health/ready.
A99: API-F21 | B99: API Contract | C99: Structurally identical lifecycle endpoints require different permissions | D99: High | E99: Code (BC) | F99: Open | G99: As reported
A100: API-F25 | B100: API Contract | C100: No API spec exists; the one artefact that does is 19% complete and has drifted | D100: High | E100: Docs | F100: Open | G100: As reported
A101: API-F26 | B101: API Contract | C101: No list endpoint reports a total, so no consumer can paginate | D101: High | E101: Additive | F101: Partially fixed | G101: Verified in code | H101: TOTAL_COL/splitTotal added in query-helpers.js and wired into 4 finance repos (final_invoice, journal_entry, proforma, smart_receivables) via commit 9c5337d, surfaced as X-Total-Count. 198 of 202 collection GETs still return a bare array
A102: API-F27 | B102: API Contract | C102: 17 list endpoints have no LIMIT at all, including /sessions and /permissions | D102: High | E102: Code (BC) | F102: Open | G102: As reported
A103: API-F3 | B103: API Contract | C103: Middleware-level errors omit request_id | D103: Medium | E103: Code | F103: Open | G103: As reported
A104: API-F4 | B104: API Contract | C104: A platform-host request to the tenant API returns 500 | D104: Medium | E104: Code | F104: Open | G104: As reported
A105: API-F7 | B105: API Contract | C105: /portal and /portals are different products | D105: Medium | E105: Code (BC) | F105: Open | G105: As reported
...

Sheet Summary
A1: Praxis LS - consolidated audit register, 2026-08-04
A2: Seven Phase-0 audits. One row per headline finding on the Register sheet.
A4: Audit | B4: Critical | C4: High | D4: Medium-High | E4: Medium | F4: Low-Medium | G4: Low | H4: Total
A5: Security | B5: =COUNTIFS(Register!$B$2:$B$206,$A5,Register!$D$2:$D$206,B$4) -> 3 | C5: =COUNTIFS(Register!$B$2:$B$206,$A5,Register!$D$2:$D$206,C$4) -> 6 | D5: =COUNTIFS(Register!$B$2:$B$206,$A5,Register!$D$2:$D$206,D$4) -> 0 | E5: =COUNTIFS(Register!$B$2:$B$206,$A5,Register!$D$2:$D$206,E$4) -> 9 | F5: =COUNTIFS(Register!$B$2:$B$206,$A5,Register!$D$2:$D$206,F$4) -> 0 | G5: =COUNTIFS(Register!$B$2:$B$206,$A5,Register!$D$2:$D$206,G$4) -> 6 | H5: =SUM(B5:G5) -> 24
A6: Data Integrity | B6: =COUNTIFS(Register!$B$2:$B$206,$A6,Register!$D$2:$D$206,B$4) -> 6 | C6: =COUNTIFS(Register!$B$2:$B$206,$A6,Register!$D$2:$D$206,C$4) -> 16 | D6: =COUNTIFS(Register!$B$2:$B$206,$A6,Register!$D$2:$D$206,D$4) -> 0 | E6: =COUNTIFS(Register!$B$2:$B$206,$A6,Register!$D$2:$D$206,E$4) -> 10 | F6: =COUNTIFS(Register!$B$2:$B$206,$A6,Register!$D$2:$D$206,F$4) -> 0 | G6: =COUNTIFS(Register!$B$2:$B$206,$A6,Register!$D$2:$D$206,G$4) -> 1 | H6: =SUM(B6:G6) -> 33
A7: Observability | B7: =COUNTIFS(Register!$B$2:$B$206,$A7,Register!$D$2:$D$206,B$4) -> 13 | C7: =COUNTIFS(Register!$B$2:$B$206,$A7,Register!$D$2:$D$206,C$4) -> 12 | D7: =COUNTIFS(Register!$B$2:$B$206,$A7,Register!$D$2:$D$206,D$4) -> 0 | E7: =COUNTIFS(Register!$B$2:$B$206,$A7,Register!$D$2:$D$206,E$4) -> 6 | F7: =COUNTIFS(Register!$B$2:$B$206,$A7,Register!$D$2:$D$206,F$4) -> 0 | G7: =COUNTIFS(Register!$B$2:$B$206,$A7,Register!$D$2:$D$206,G$4) -> 0 | H7: =SUM(B7:G7) -> 31
A8: API Contract | B8: =COUNTIFS(Register!$B$2:$B$206,$A8,Register!$D$2:$D$206,B$4) -> 5 | C8: =COUNTIFS(Register!$B$2:$B$206,$A8,Register!$D$2:$D$206,C$4) -> 8 | D8: =COUNTIFS(Register!$B$2:$B$206,$A8,Register!$D$2:$D$206,D$4) -> 0 | E8: =COUNTIFS(Register!$B$2:$B$206,$A8,Register!$D$2:$D$206,E$4) -> 13 | F8: =COUNTIFS(Register!$B$2:$B$206,$A8,Register!$D$2:$D$206,F$4) -> 0 | G8: =COUNTIFS(Register!$B$2:$B$206,$A8,Register!$D$2:$D$206,G$4) -> 4 | H8: =SUM(B8:G8) -> 30
A9: Perf & Architecture | B9: =COUNTIFS(Register!$B$2:$B$206,$A9,Register!$D$2:$D$206,B$4) -> 3 | C9: =COUNTIFS(Register!$B$2:$B$206,$A9,Register!$D$2:$D$206,C$4) -> 9 | D9: =COUNTIFS(Register!$B$2:$B$206,$A9,Register!$D$2:$D$206,D$4) -> 0 | E9: =COUNTIFS(Register!$B$2:$B$206,$A9,Register!$D$2:$D$206,E$4) -> 6 | F9: =COUNTIFS(Register!$B$2:$B$206,$A9,Register!$D$2:$D$206,F$4) -> 0 | G9: =COUNTIFS(Register!$B$2:$B$206,$A9,Register!$D$2:$D$206,G$4) -> 2 | H9: =SUM(B9:G9) -> 20
A10: Test & CI/CD | B10: =COUNTIFS(Register!$B$2:$B$206,$A10,Register!$D$2:$D$206,B$4) -> 7 | C10: =COUNTIFS(Register!$B$2:$B$206,$A10,Register!$D$2:$D$206,C$4) -> 19 | D10: =COUNTIFS(Register!$B$2:$B$206,$A10,Register!$D$2:$D$206,D$4) -> 2 | E10: =COUNTIFS(Register!$B$2:$B$206,$A10,Register!$D$2:$D$206,E$4) -> 12 | F10: =COUNTIFS(Register!$B$2:$B$206,$A10,Register!$D$2:$D$206,F$4) -> 3 | G10: =COUNTIFS(Register!$B$2:$B$206,$A10,Register!$D$2:$D$206,G$4) -> 4 | H10: =SUM(B10:G10) -> 47
A11: Desktop UI | B11: =COUNTIFS(Register!$B$2:$B$206,$A11,Register!$D$2:$D$206,B$4) -> 5 | C11: =COUNTIFS(Register!$B$2:$B$206,$A11,Register!$D$2:$D$206,C$4) -> 7 | D11: =COUNTIFS(Register!$B$2:$B$206,$A11,Register!$D$2:$D$206,D$4) -> 0 | E11: =COUNTIFS(Register!$B$2:$B$206,$A11,Register!$D$2:$D$206,E$4) -> 8 | F11: =COUNTIFS(Register!$B$2:$B$206,$A11,Register!$D$2:$D$206,F$4) -> 0 | G11: =COUNTIFS(Register!$B$2:$B$206,$A11,Register!$D$2:$D$206,G$4) -> 0 | H11: =SUM(B11:G11) -> 20
A12: Total | B12: =SUM(B5:B11) -> 42 | C12: =SUM(C5:C11) -> 77 | D12: =SUM(D5:D11) -> 2 | E12: =SUM(E5:E11) -> 64 | F12: =SUM(F5:F11) -> 3 | G12: =SUM(G5:G11) -> 17 | H12: =SUM(H5:H11) -> 205
A14: Status roll-up
A15: Open | B15: =COUNTIF(Register!$F$2:$F$206,$A15) -> 164
A16: Partially fixed | B16: =COUNTIF(Register!$F$2:$F$206,$A16) -> 5
A17: Fixed | B17: =COUNTIF(Register!$F$2:$F$206,"Fixed") -> 31
A18: Largely fixed (superseded) | B18: =COUNTIF(Register!$F$2:$F$206,$A18) -> 0
A19: Closed | B19: =COUNTIF(Register!$F$2:$F$206,$A19) -> 3
A20: Independently verified in code | B20: =COUNTIF(Register!$G$2:$G$206,"Verified in code") -> 40
